easy_jsonrpc/__init__.py
easy_jsonrpc/client.py
easy_jsonrpc/common.py
easy_jsonrpc/server.py
easy_jsonrpc-0.1.3.dist-info/METADATA
easy_jsonrpc-0.1.3.dist-info/WHEEL
easy_jsonrpc-0.1.3.dist-info/top_level.txt
easy_jsonrpc-0.1.3.dist-info/RECORD
