Metadata-Version: 2.1
Name: easy-jsonrpc
Version: 0.1.3
Summary: Easy JSON-RPC library for Python and Go interoperability
Home-page: https://github.com/CHOJUNGHO96/easy-jsonrpc.git
Author: ChoJungHo
Author-email: jo4186@naver.com
Keywords: jsonrpc,rpc,api,golang,interoperability
Classifier: Programming Language :: Python :: 3
Classifier: Programming Language :: Python :: 3.5
Classifier: Programming Language :: Python :: 3.6
Classifier: Programming Language :: Python :: 3.7
Classifier: Programming Language :: Python :: 3.8
Classifier: Programming Language :: Python :: 3.9
Classifier: License :: OSI Approved :: MIT License
Classifier: Operating System :: OS Independent
Requires-Python: >=3.5
Requires-Dist: jsonrpclib-pelix >=0.4.0
